{
  "reliquary:InNTurnsDeath": {
    "NAME": "",
    "DESCRIPTIONS": [
      "In #b",
      " turns, die."
    ]
  },
  "reliquary:InvincibleTurns": {
    "NAME": "Непобедимость",
    "DESCRIPTIONS": [
      "Не получает урона в этом ходу.",
      "Не получает урона следующие #b",
      " хода."
    ]
  },
  "reliquary:LesserDuplication": {
    "NAME": "Услабленное удвоение",
    "DESCRIPTIONS": [
      "Следующая разыгранная карта, со стоимостью 0 или 1, в этом ходу, будет разыграна дважды.",
      "Следующие #b",
      " разыгранные карты, со стоимостью 0 или 1, в этом ходу, будут разыграны дважды."
    ]
  },
  "reliquary:ReduceColorlessCost": {
    "NAME": "Бледность",
    "DESCRIPTIONS": [
      "Следующая разыгранная Бесцветная карта будет стоить на #b1 меньше.",
      "Следующие #b",
      " разыгранные Бесцветные карты стоят на #b1 меньше."
    ]
  },
  "reliquary:StudyPlus": {
    "NAME": "Обучение",
    "DESCRIPTIONS": [
      "В конце хода замешивает #b",
      " #yОзарение+ в стопку добору."
    ]
  },
  "reliquary:Taunt": {
    "NAME": "Насмешка",
    "DESCRIPTIONS": [
      "Остальные враги не могут стать целью ваших карт пока этот враг не умрёт.",
      "Другой враг #r@насмехается@ надо мной!"
    ]
  },
  "reliquary:Triumph": {
    "NAME": "Триумф",
    "DESCRIPTIONS": [
      "Множитель урона #yБожественности повышен на #b",
      ", и теперь составляет #b",
      "."
    ]
  }
}